data_alchemy/__init__.py
data_alchemy/__version__.py
data_alchemy/fetch/__init__.py
data_alchemy/fetch/archiver/__init__.py
data_alchemy/fetch/collector/__init__.py
data_alchemy/fetch/collector/main.py
data_alchemy/fetch/collector/models.py
data_alchemy/fetch/collector/README.md
data_alchemy/fetch/collector/schema.json
data_alchemy/fetch/downloader/__init__.py
data_alchemy/fetch/downloader/main.py
data_alchemy/fetch/downloader/models.py
data_alchemy/fetch/utils.py
data_alchemy/ingest/__init__.py
data_alchemy/ingest/cloud_storage/__init__.py
data_alchemy/ingest/cloud_storage/main.py
data_alchemy/ingest/cloud_storage/models.py
data_alchemy/ingest/cloud_storage/provider/__init__.py
data_alchemy/ingest/cloud_storage/provider/_base_storage.py
data_alchemy/ingest/cloud_storage/provider/aws_storage.py
data_alchemy/ingest/cloud_storage/provider/azure_storage.py
data_alchemy/ingest/cloud_storage/provider/gcloud_storage.py
data_alchemy/ingest/cloud_storage/provider/local_storage.py
data_alchemy/ingest/cloud_storage/provider/models.py
data_alchemy/ingest/database/__init__.py
data_alchemy/ingest/database/main.py
data_alchemy/ingest/database/models.py
data_alchemy/ingest/database/provider/__init__.py
data_alchemy/ingest/database/provider/_base_db.py
data_alchemy/ingest/database/provider/models.py
data_alchemy/ingest/database/provider/mongo_db.py
data_alchemy/ingest/database/provider/supabase_db.py
data_alchemy/store_configs/__init__.py
data_alchemy/store_configs/configure_html.py
data_alchemy/store_configs/models.py
data_alchemy/transform/__init__.py
data_alchemy/transform/main.py
data_alchemy/transform/sample_config.yaml
data_alchemy/transform/transformer/__init__.py
data_alchemy/transform/transformer/base_transformer.py
data_alchemy/transform/transformer/csv_transformer.py
data_alchemy/transform/transformer/html/__init__.py
data_alchemy/transform/transformer/html/html_transformer.py
data_alchemy/transform/transformer/html/parser/__init__.py
data_alchemy-0.0.2.dist-info/LICENSE
data_alchemy-0.0.2.dist-info/METADATA
data_alchemy-0.0.2.dist-info/WHEEL
data_alchemy-0.0.2.dist-info/RECORD
